{
  "zonesCrossNominees": [
    [
      {
        "inZone": [
          true,
          false
        ],
        "crossingPair": [
          {
            "time": "2018-05-26T11:23:21Z",
            "lat": 43.83001667,
            "fix": 68,
            "lng": 16.63751667,
            "alt": 757
          },
          {
            "time": "2018-05-26T11:23:22Z",
            "lat": 43.82998333,
            "fix": 69,
            "lng": 16.6374,
            "alt": 756
          }
        ]
      }
    ],
    [
      {
        "inZone": [
          true,
          false
        ],
        "crossingPair": [
          {
            "time": "2018-05-26T11:24:45Z",
            "lat": 43.8294,
            "fix": 152,
            "lng": 16.62841667,
            "alt": 715
          },
          {
            "time": "2018-05-26T11:24:46Z",
            "lat": 43.82936667,
            "fix": 153,
            "lng": 16.62833333,
            "alt": 713
          }
        ]
      }
    ],
    [
      {
        "inZone": [
          false,
          true
        ],
        "crossingPair": [
          {
            "time": "2018-05-26T11:27:10Z",
            "lat": 43.8259,
            "fix": 297,
            "lng": 16.61915,
            "alt": 678
          },
          {
            "time": "2018-05-26T11:27:11Z",
            "lat": 43.82588333,
            "fix": 298,
            "lng": 16.61906667,
            "alt": 678
          }
        ]
      },
      {
        "inZone": [
          true,
          false
        ],
        "crossingPair": [
          {
            "time": "2018-05-26T11:27:18Z",
            "lat": 43.82571667,
            "fix": 305,
            "lng": 16.61938333,
            "alt": 672
          },
          {
            "time": "2018-05-26T11:27:19Z",
            "lat": 43.82578333,
            "fix": 306,
            "lng": 16.6195,
            "alt": 672
          }
        ]
      },
      {
        "inZone": [
          false,
          true
        ],
        "crossingPair": [
          {
            "time": "2018-05-26T11:28:13Z",
            "lat": 43.82581667,
            "fix": 360,
            "lng": 16.61935,
            "alt": 653
          },
          {
            "time": "2018-05-26T11:28:14Z",
            "lat": 43.8258,
            "fix": 361,
            "lng": 16.61926667,
            "alt": 652
          }
        ]
      },
      {
        "inZone": [
          true,
          false
        ],
        "crossingPair": [
          {
            "time": "2018-05-26T11:28:50Z",
            "lat": 43.82496667,
            "fix": 397,
            "lng": 16.62035,
            "alt": 651
          },
          {
            "time": "2018-05-26T11:28:51Z",
            "lat": 43.82498333,
            "fix": 398,
            "lng": 16.62045,
            "alt": 651
          }
        ]
      },
      {
        "inZone": [
          false,
          true
        ],
        "crossingPair": [
          {
            "time": "2018-05-26T11:28:59Z",
            "lat": 43.82465,
            "fix": 406,
            "lng": 16.62073333,
            "alt": 645
          },
          {
            "time": "2018-05-26T11:29:00Z",
            "lat": 43.82463333,
            "fix": 407,
            "lng": 16.62068333,
            "alt": 646
          }
        ]
      },
      {
        "inZone": [
          true,
          false
        ],
        "crossingPair": [
          {
            "time": "2018-05-26T11:29:17Z",
            "lat": 43.82526667,
            "fix": 424,
            "lng": 16.61998333,
            "alt": 656
          },
          {
            "time": "2018-05-26T11:29:18Z",
            "lat": 43.8253,
            "fix": 425,
            "lng": 16.6201,
            "alt": 657
          }
        ]
      }
    ],
    [],
    [],
    [],
    [],
    [
      {
        "inZone": [
          false,
          true
        ],
        "crossingPair": [
          {
            "time": "2018-05-26T11:25:07Z",
            "lat": 43.82851667,
            "fix": 174,
            "lng": 16.62626667,
            "alt": 685
          },
          {
            "time": "2018-05-26T11:25:08Z",
            "lat": 43.82848333,
            "fix": 175,
            "lng": 16.62613333,
            "alt": 687
          }
        ]
      },
      {
        "inZone": [
          true,
          false
        ],
        "crossingPair": [
          {
            "time": "2018-05-26T11:31:57Z",
            "lat": 43.8222,
            "fix": 584,
            "lng": 16.62873333,
            "alt": 565
          },
          {
            "time": "2018-05-26T11:31:58Z",
            "lat": 43.82218333,
            "fix": 585,
            "lng": 16.62881667,
            "alt": 564
          }
        ]
      }
    ],
    []
  ],
  "zonesCrossExcluded": [],
  "startSelected": [
    "2018-05-26T11:00:00Z",
    {
      "inZone": [
        true,
        false
      ],
      "crossingPair": [
        {
          "time": "2018-05-26T11:24:45Z",
          "lat": 43.8294,
          "fix": 152,
          "lng": 16.62841667,
          "alt": 715
        },
        {
          "time": "2018-05-26T11:24:46Z",
          "lat": 43.82936667,
          "fix": 153,
          "lng": 16.62833333,
          "alt": 713
        }
      ]
    }
  ],
  "zonesCrossSelected": [
    {
      "inZone": [
        true,
        false
      ],
      "crossingPair": [
        {
          "time": "2018-05-26T11:23:21Z",
          "lat": 43.83001667,
          "fix": 68,
          "lng": 16.63751667,
          "alt": 757
        },
        {
          "time": "2018-05-26T11:23:22Z",
          "lat": 43.82998333,
          "fix": 69,
          "lng": 16.6374,
          "alt": 756
        }
      ]
    },
    {
      "inZone": [
        true,
        false
      ],
      "crossingPair": [
        {
          "time": "2018-05-26T11:24:45Z",
          "lat": 43.8294,
          "fix": 152,
          "lng": 16.62841667,
          "alt": 715
        },
        {
          "time": "2018-05-26T11:24:46Z",
          "lat": 43.82936667,
          "fix": 153,
          "lng": 16.62833333,
          "alt": 713
        }
      ]
    },
    {
      "inZone": [
        false,
        true
      ],
      "crossingPair": [
        {
          "time": "2018-05-26T11:27:10Z",
          "lat": 43.8259,
          "fix": 297,
          "lng": 16.61915,
          "alt": 678
        },
        {
          "time": "2018-05-26T11:27:11Z",
          "lat": 43.82588333,
          "fix": 298,
          "lng": 16.61906667,
          "alt": 678
        }
      ]
    },
    null,
    null,
    null,
    null,
    null,
    null
  ],
  "startNominees": [
    [
      "2018-05-26T11:00:00Z",
      [
        {
          "inZone": [
            true,
            false
          ],
          "crossingPair": [
            {
              "time": "2018-05-26T11:24:45Z",
              "lat": 43.8294,
              "fix": 152,
              "lng": 16.62841667,
              "alt": 715
            },
            {
              "time": "2018-05-26T11:24:46Z",
              "lat": 43.82936667,
              "fix": 153,
              "lng": 16.62833333,
              "alt": 713
            }
          ]
        }
      ]
    ]
  ]
}
