[
  [
    [
      "98",
      "Tomas Svoboda"
    ],
    {
      "reach": "13.644542 km",
      "frac": 1
    }
  ],
  [
    [
      "101",
      "Tomaž Toplak"
    ],
    {
      "reach": "12.541542 km",
      "frac": 0.91916182
    }
  ],
  [
    [
      "16",
      "Bruno Matos"
    ],
    {
      "reach": "11.093542 km",
      "frac": 0.8130388
    }
  ],
  [
    [
      "57",
      "Lara Leban"
    ],
    {
      "reach": "9.101542 km",
      "frac": 0.66704635
    }
  ],
  [
    [
      "72",
      "Mitja Jančič"
    ],
    {
      "reach": "9.018542 km",
      "frac": 0.66096334
    }
  ],
  [
    [
      "114",
      "Joan Brito"
    ],
    {
      "reach": "8.216542 km",
      "frac": 0.60218525
    }
  ],
  [
    [
      "41",
      "Ivo Duarte"
    ],
    {
      "reach": "8.208542 km",
      "frac": 0.60159894
    }
  ],
  [
    [
      "26",
      "Dušan Durkovič"
    ],
    {
      "reach": "6.794542 km",
      "frac": 0.49796776
    }
  ],
  [
    [
      "86",
      "Sandi Krč"
    ],
    {
      "reach": "6.773542 km",
      "frac": 0.49642868
    }
  ],
  [
    [
      "4",
      "Alojz Tovornik"
    ],
    {
      "reach": "5.521542 km",
      "frac": 0.40467038
    }
  ],
  [
    [
      "13",
      "Balazs Szatmari"
    ],
    {
      "reach": "4.795542 km",
      "frac": 0.35146229
    }
  ],
  [
    [
      "37",
      "Igor Eržen"
    ],
    {
      "reach": "4.182542 km",
      "frac": 0.3065359
    }
  ],
  [
    [
      "74",
      "Nuno Filipe da Fonseca Bastos Gomes"
    ],
    {
      "reach": "3.508542 km",
      "frac": 0.25713886
    }
  ],
  [
    [
      "21",
      "Damir Kalinger"
    ],
    {
      "reach": "3.443542 km",
      "frac": 0.25237505
    }
  ],
  [
    [
      "9",
      "Antoni Buljan"
    ],
    {
      "reach": "3.335542 km",
      "frac": 0.2444598
    }
  ],
  [
    [
      "73",
      "Mitja Jug"
    ],
    {
      "reach": "3.058542 km",
      "frac": 0.22415864
    }
  ],
  [
    [
      "54",
      "Krešo  Kovačič"
    ],
    {
      "reach": "2.904542 km",
      "frac": 0.21287208
    }
  ],
  [
    [
      "80",
      "Ricardo Nicolau Soares Terra de Oliveira Figueiredo"
    ],
    {
      "reach": "2.648542 km",
      "frac": 0.19411
    }
  ],
  [
    [
      "46",
      "Jerko Odžak"
    ],
    {
      "reach": "2.257542 km",
      "frac": 0.16545385
    }
  ],
  [
    [
      "23",
      "David Šiljeg"
    ],
    {
      "reach": "2.185542 km",
      "frac": 0.16017701
    }
  ],
  [
    [
      "40",
      "Ivica Huljek"
    ],
    {
      "reach": "0.886542 km",
      "frac": 0.06497411
    }
  ]
]
