[
  [
    [
      "16",
      "Bruno Matos"
    ],
    {
      "breakdown": {
        "time": 496.2,
        "reach": 398.288,
        "distance": 398.288,
        "leading": 101,
        "effort": 0,
        "arrival": 0
      },
      "stoppedAlt": null,
      "penaltyReason": "",
      "velocity": {
        "gs": "2018-05-27T11:00:00Z",
        "ssVelocity": "24.33 km / h",
        "ssElapsed": "1.058423 h",
        "gsElapsed": "1.077888 h",
        "es": "2018-05-27T12:04:40.395858258554Z",
        "ss": "2018-05-27T11:01:10.072620696286Z",
        "ssDistance": "25.749 km",
        "gsVelocity": "23.90 km / h"
      },
      "total": 996,
      "landedDistance": "26.388 km",
      "penalties": [],
      "place": "1",
      "reachDistance": "26.388 km"
    }
  ],
  [
    [
      "98",
      "Tomas Svoboda"
    ],
    {
      "breakdown": {
        "time": 441,
        "reach": 398.288,
        "distance": 398.288,
        "leading": 98.3,
        "effort": 0,
        "arrival": 0
      },
      "stoppedAlt": null,
      "penaltyReason": "",
      "velocity": {
        "gs": "2018-05-27T11:00:00Z",
        "ssVelocity": "23.58 km / h",
        "ssElapsed": "1.091845 h",
        "gsElapsed": "1.116429 h",
        "es": "2018-05-27T12:06:59.144456166262Z",
        "ss": "2018-05-27T11:01:28.504072245196Z",
        "ssDistance": "25.749 km",
        "gsVelocity": "23.10 km / h"
      },
      "total": 938,
      "landedDistance": "26.388 km",
      "penalties": [],
      "place": "2",
      "reachDistance": "26.388 km"
    }
  ],
  [
    [
      "26",
      "Dušan Durkovič"
    ],
    {
      "breakdown": {
        "time": 327.6,
        "reach": 398.288,
        "distance": 398.288,
        "leading": 105.3,
        "effort": 0,
        "arrival": 0
      },
      "stoppedAlt": null,
      "penaltyReason": "",
      "velocity": {
        "gs": "2018-05-27T11:00:00Z",
        "ssVelocity": "20.05 km / h",
        "ssElapsed": "1.284002 h",
        "gsElapsed": "1.283584 h",
        "es": "2018-05-27T12:17:00.900857355684Z",
        "ss": "2018-05-27T10:59:58.493091705645Z",
        "ssDistance": "25.749 km",
        "gsVelocity": "20.10 km / h"
      },
      "total": 831,
      "landedDistance": "26.388 km",
      "penalties": [],
      "place": "3",
      "reachDistance": "26.388 km"
    }
  ],
  [
    [
      "4",
      "Alojz Tovornik"
    ],
    {
      "breakdown": {
        "time": 265.1,
        "reach": 398.288,
        "distance": 398.288,
        "leading": 62.1,
        "effort": 0,
        "arrival": 0
      },
      "stoppedAlt": null,
      "penaltyReason": "",
      "velocity": {
        "gs": "2018-05-27T11:00:00Z",
        "ssVelocity": "19.28 km / h",
        "ssElapsed": "1.335342 h",
        "gsElapsed": "1.407919 h",
        "es": "2018-05-27T12:24:28.506649155718Z",
        "ss": "2018-05-27T11:04:21.274912373434Z",
        "ssDistance": "25.749 km",
        "gsVelocity": "18.30 km / h"
      },
      "total": 725,
      "landedDistance": "26.388 km",
      "penalties": [],
      "place": "4",
      "reachDistance": "26.388 km"
    }
  ],
  [
    [
      "101",
      "Tomaž Toplak"
    ],
    {
      "breakdown": {
        "time": 269.8,
        "reach": 398.288,
        "distance": 398.288,
        "leading": 39.6,
        "effort": 0,
        "arrival": 0
      },
      "stoppedAlt": null,
      "penaltyReason": "",
      "velocity": {
        "gs": "2018-05-27T11:00:00Z",
        "ssVelocity": "22.68 km / h",
        "ssElapsed": "1.135435 h",
        "gsElapsed": "1.397867 h",
        "es": "2018-05-27T12:23:52.319696651864Z",
        "ss": "2018-05-27T11:15:44.755297397846Z",
        "ssDistance": "25.749 km",
        "gsVelocity": "18.40 km / h"
      },
      "total": 708,
      "landedDistance": "26.388 km",
      "penalties": [],
      "place": "5",
      "reachDistance": "26.388 km"
    }
  ],
  [
    [
      "74",
      "Nuno Filipe da Fonseca Bastos Gomes"
    ],
    {
      "breakdown": {
        "time": 243.7,
        "reach": 398.288,
        "distance": 398.288,
        "leading": 39,
        "effort": 0,
        "arrival": 0
      },
      "stoppedAlt": null,
      "penaltyReason": "",
      "velocity": {
        "gs": "2018-05-27T11:00:00Z",
        "ssVelocity": "20.23 km / h",
        "ssElapsed": "1.272754 h",
        "gsElapsed": "1.454838 h",
        "es": "2018-05-27T12:27:17.415058689468Z",
        "ss": "2018-05-27T11:10:55.499334281524Z",
        "ssDistance": "25.749 km",
        "gsVelocity": "17.70 km / h"
      },
      "total": 681,
      "landedDistance": "26.388 km",
      "penalties": [],
      "place": "6",
      "reachDistance": "26.388 km"
    }
  ],
  [
    [
      "73",
      "Mitja Jug"
    ],
    {
      "breakdown": {
        "time": 194,
        "reach": 398.288,
        "distance": 398.288,
        "leading": 44.2,
        "effort": 0,
        "arrival": 0
      },
      "stoppedAlt": null,
      "penaltyReason": "",
      "velocity": {
        "gs": "2018-05-27T11:00:00Z",
        "ssVelocity": "16.95 km / h",
        "ssElapsed": "1.518938 h",
        "gsElapsed": "1.571306 h",
        "es": "2018-05-27T12:34:16.70119084755Z",
        "ss": "2018-05-27T11:03:08.526060691163Z",
        "ssDistance": "25.749 km",
        "gsVelocity": "16.40 km / h"
      },
      "total": 637,
      "landedDistance": "26.388 km",
      "penalties": [],
      "place": "7",
      "reachDistance": "26.388 km"
    }
  ],
  [
    [
      "114",
      "Joan Brito"
    ],
    {
      "breakdown": {
        "time": 169.7,
        "reach": 398.288,
        "distance": 398.288,
        "leading": 60.6,
        "effort": 0,
        "arrival": 0
      },
      "stoppedAlt": null,
      "penaltyReason": "",
      "velocity": {
        "gs": "2018-05-27T11:00:00Z",
        "ssVelocity": "15.90 km / h",
        "ssElapsed": "1.619001 h",
        "gsElapsed": "1.631988 h",
        "es": "2018-05-27T12:37:55.156203702864Z",
        "ss": "2018-05-27T11:00:46.754039570122Z",
        "ssDistance": "25.749 km",
        "gsVelocity": "15.80 km / h"
      },
      "total": 629,
      "landedDistance": "26.388 km",
      "penalties": [],
      "place": "8",
      "reachDistance": "26.388 km"
    }
  ],
  [
    [
      "9",
      "Antoni Buljan"
    ],
    {
      "breakdown": {
        "time": 190.8,
        "reach": 398.288,
        "distance": 398.288,
        "leading": 25.7,
        "effort": 0,
        "arrival": 0
      },
      "stoppedAlt": null,
      "penaltyReason": "",
      "velocity": {
        "gs": "2018-05-27T11:00:00Z",
        "ssVelocity": "19.66 km / h",
        "ssElapsed": "1.309889 h",
        "gsElapsed": "1.579185 h",
        "es": "2018-05-27T12:34:45.06556475656Z",
        "ss": "2018-05-27T11:16:09.465490922405Z",
        "ssDistance": "25.749 km",
        "gsVelocity": "16.30 km / h"
      },
      "total": 615,
      "landedDistance": "26.388 km",
      "penalties": [],
      "place": "9",
      "reachDistance": "26.388 km"
    }
  ],
  [
    [
      "72",
      "Mitja Jančič"
    ],
    {
      "breakdown": {
        "time": 173,
        "reach": 398.288,
        "distance": 398.288,
        "leading": 36.1,
        "effort": 0,
        "arrival": 0
      },
      "stoppedAlt": null,
      "penaltyReason": "",
      "velocity": {
        "gs": "2018-05-27T11:00:00Z",
        "ssVelocity": "16.10 km / h",
        "ssElapsed": "1.599686 h",
        "gsElapsed": "1.623645 h",
        "es": "2018-05-27T12:37:25.123494424146Z",
        "ss": "2018-05-27T11:01:26.254793717659Z",
        "ssDistance": "25.749 km",
        "gsVelocity": "15.90 km / h"
      },
      "total": 607,
      "landedDistance": "26.388 km",
      "penalties": [],
      "place": "10",
      "reachDistance": "26.388 km"
    }
  ],
  [
    [
      "95",
      "Stojan Kranjc"
    ],
    {
      "breakdown": {
        "time": 120,
        "reach": 398.288,
        "distance": 398.288,
        "leading": 19.1,
        "effort": 0,
        "arrival": 0
      },
      "stoppedAlt": null,
      "penaltyReason": "",
      "velocity": {
        "gs": "2018-05-27T11:00:00Z",
        "ssVelocity": "17.25 km / h",
        "ssElapsed": "1.493138 h",
        "gsElapsed": "1.763254 h",
        "es": "2018-05-27T12:45:47.715130258676Z",
        "ss": "2018-05-27T11:16:12.417180679478Z",
        "ssDistance": "25.749 km",
        "gsVelocity": "14.60 km / h"
      },
      "total": 537,
      "landedDistance": "26.388 km",
      "penalties": [],
      "place": "11",
      "reachDistance": "26.388 km"
    }
  ],
  [
    [
      "54",
      "Krešo  Kovačič"
    ],
    {
      "breakdown": {
        "time": 0,
        "reach": 374.153,
        "distance": 374.153,
        "leading": 53.6,
        "effort": 0,
        "arrival": 0
      },
      "stoppedAlt": "0.000 m",
      "penaltyReason": "",
      "velocity": {
        "gs": "2018-05-27T11:00:00Z",
        "ssVelocity": null,
        "ssElapsed": null,
        "gsElapsed": null,
        "es": null,
        "ss": "2018-05-27T11:03:42.532627074644Z",
        "ssDistance": null,
        "gsVelocity": null
      },
      "total": 428,
      "landedDistance": "24.676 km",
      "penalties": [],
      "place": "12",
      "reachDistance": "24.789 km"
    }
  ],
  [
    [
      "63",
      "Marketa Tomaskova"
    ],
    {
      "breakdown": {
        "time": 16.7,
        "reach": 398.288,
        "distance": 398.288,
        "leading": 9.1,
        "effort": 0,
        "arrival": 0
      },
      "stoppedAlt": null,
      "penaltyReason": "",
      "velocity": {
        "gs": "2018-05-27T11:00:00Z",
        "ssVelocity": "12.62 km / h",
        "ssElapsed": "2.040778 h",
        "gsElapsed": "2.064247 h",
        "es": "2018-05-27T13:03:51.288816090004Z",
        "ss": "2018-05-27T11:01:24.487721833995Z",
        "ssDistance": "25.749 km",
        "gsVelocity": "12.50 km / h"
      },
      "total": 424,
      "landedDistance": "26.388 km",
      "penalties": [],
      "place": "13",
      "reachDistance": "26.388 km"
    }
  ],
  [
    [
      "37",
      "Igor Eržen"
    ],
    {
      "breakdown": {
        "time": 0,
        "reach": 348.51,
        "distance": 348.51,
        "leading": 54.2,
        "effort": 0,
        "arrival": 0
      },
      "stoppedAlt": "367.000 m",
      "penaltyReason": "",
      "velocity": {
        "gs": "2018-05-27T11:00:00Z",
        "ssVelocity": null,
        "ssElapsed": null,
        "gsElapsed": null,
        "es": null,
        "ss": "2018-05-27T11:02:31.573550196073Z",
        "ssDistance": null,
        "gsVelocity": null
      },
      "total": 403,
      "landedDistance": "23.090 km",
      "penalties": [],
      "place": "14",
      "reachDistance": "23.090 km"
    }
  ],
  [
    [
      "41",
      "Ivo Duarte"
    ],
    {
      "breakdown": {
        "time": 0,
        "reach": 336.315,
        "distance": 336.315,
        "leading": 63.7,
        "effort": 0,
        "arrival": 0
      },
      "stoppedAlt": "381.000 m",
      "penaltyReason": "",
      "velocity": {
        "gs": "2018-05-27T11:00:00Z",
        "ssVelocity": null,
        "ssElapsed": null,
        "gsElapsed": null,
        "es": null,
        "ss": "2018-05-27T11:03:12.431339043353Z",
        "ssDistance": null,
        "gsVelocity": null
      },
      "total": 400,
      "landedDistance": "22.283 km",
      "penalties": [],
      "place": "15",
      "reachDistance": "22.282 km"
    }
  ],
  [
    [
      "57",
      "Lara Leban"
    ],
    {
      "breakdown": {
        "time": 0,
        "reach": 346.472,
        "distance": 346.472,
        "leading": 28,
        "effort": 0,
        "arrival": 0
      },
      "stoppedAlt": "380.000 m",
      "penaltyReason": "",
      "velocity": {
        "gs": "2018-05-27T11:00:00Z",
        "ssVelocity": null,
        "ssElapsed": null,
        "gsElapsed": null,
        "es": null,
        "ss": "2018-05-27T11:04:19.260597647989Z",
        "ssDistance": null,
        "gsVelocity": null
      },
      "total": 374,
      "landedDistance": "22.955 km",
      "penalties": [],
      "place": "16",
      "reachDistance": "22.955 km"
    }
  ],
  [
    [
      "23",
      "David Šiljeg"
    ],
    {
      "breakdown": {
        "time": 0,
        "reach": 240.819,
        "distance": 240.819,
        "leading": 0,
        "effort": 0,
        "arrival": 0
      },
      "stoppedAlt": "387.000 m",
      "penaltyReason": "",
      "velocity": {
        "gs": "2018-05-27T11:00:00Z",
        "ssVelocity": null,
        "ssElapsed": null,
        "gsElapsed": null,
        "es": null,
        "ss": "2018-05-27T12:17:40.95796527115Z",
        "ssDistance": null,
        "gsVelocity": null
      },
      "total": 241,
      "landedDistance": "14.248 km",
      "penalties": [],
      "place": "17",
      "reachDistance": "15.955 km"
    }
  ],
  [
    [
      "80",
      "Ricardo Nicolau Soares Terra de Oliveira Figueiredo"
    ],
    {
      "breakdown": {
        "time": 0,
        "reach": 48.545,
        "distance": 48.545,
        "leading": 0,
        "effort": 0,
        "arrival": 0
      },
      "stoppedAlt": "532.000 m",
      "penaltyReason": "",
      "velocity": {
        "gs": "2018-05-27T11:00:00Z",
        "ssVelocity": null,
        "ssElapsed": null,
        "gsElapsed": null,
        "es": null,
        "ss": "2018-05-27T13:10:39.301341708962Z",
        "ssDistance": null,
        "gsVelocity": null
      },
      "total": 49,
      "landedDistance": "3.214 km",
      "penalties": [],
      "place": "18",
      "reachDistance": "3.216 km"
    }
  ],
  [
    [
      "46",
      "Jerko Odžak"
    ],
    {
      "breakdown": {
        "time": 0,
        "reach": 28.788,
        "distance": 28.788,
        "leading": 0,
        "effort": 0,
        "arrival": 0
      },
      "stoppedAlt": "484.000 m",
      "penaltyReason": "",
      "velocity": {
        "gs": "2018-05-27T11:00:00Z",
        "ssVelocity": null,
        "ssElapsed": null,
        "gsElapsed": null,
        "es": null,
        "ss": "2018-05-27T12:09:10.020890150844Z",
        "ssDistance": null,
        "gsVelocity": null
      },
      "total": 29,
      "landedDistance": "-0.044 km",
      "penalties": [],
      "place": "19",
      "reachDistance": "1.907 km"
    }
  ],
  [
    [
      "40",
      "Ivica Huljek"
    ],
    {
      "breakdown": {
        "time": 0,
        "reach": 15.093,
        "distance": 15.093,
        "leading": 0,
        "effort": 0,
        "arrival": 0
      },
      "stoppedAlt": "0.000 m",
      "penaltyReason": "",
      "velocity": {
        "gs": "2018-05-27T11:00:00Z",
        "ssVelocity": null,
        "ssElapsed": null,
        "gsElapsed": null,
        "es": null,
        "ss": "2018-05-27T11:05:10.414112917032Z",
        "ssDistance": null,
        "gsVelocity": null
      },
      "total": 15,
      "landedDistance": "-0.195 km",
      "penalties": [],
      "place": "20=",
      "reachDistance": "0.172 km"
    }
  ],
  [
    [
      "91",
      "Slava Jelić"
    ],
    {
      "breakdown": {
        "time": 0,
        "reach": 15.093,
        "distance": 15.093,
        "leading": 0,
        "effort": 0,
        "arrival": 0
      },
      "stoppedAlt": null,
      "penaltyReason": "",
      "velocity": null,
      "total": 15,
      "landedDistance": "0.000 km",
      "penalties": [],
      "place": "20=",
      "reachDistance": "0.000 km"
    }
  ]
]
