[
  [
    [
      "16",
      "Bruno Matos"
    ],
    {
      "breakdown": {
        "time": 369.6,
        "reach": 431.276,
        "distance": 431.276,
        "leading": 199,
        "effort": 0,
        "arrival": 0
      },
      "velocity": {
        "gs": "2018-05-27T11:00:00Z",
        "ssVelocity": "24.32 km / h",
        "ssElapsed": "1.058611 h",
        "gsElapsed": "1.078056 h",
        "es": "2018-05-27T12:04:41Z",
        "ss": "2018-05-27T11:01:10Z",
        "ssDistance": "25.749 km",
        "gsVelocity": "23.90 km / h"
      },
      "total": 1000,
      "landedDistance": "26.388 km",
      "place": "1",
      "reachDistance": "26.388 km"
    }
  ],
  [
    [
      "98",
      "Tomas Svoboda"
    ],
    {
      "breakdown": {
        "time": 328.5,
        "reach": 431.276,
        "distance": 431.276,
        "leading": 198.9,
        "effort": 0,
        "arrival": 0
      },
      "velocity": {
        "gs": "2018-05-27T11:00:00Z",
        "ssVelocity": "23.58 km / h",
        "ssElapsed": "1.092222 h",
        "gsElapsed": "1.116667 h",
        "es": "2018-05-27T12:07:00Z",
        "ss": "2018-05-27T11:01:28Z",
        "ssDistance": "25.749 km",
        "gsVelocity": "23.10 km / h"
      },
      "total": 959,
      "landedDistance": "26.388 km",
      "place": "2",
      "reachDistance": "26.388 km"
    }
  ],
  [
    [
      "26",
      "Dušan Durkovič"
    ],
    {
      "breakdown": {
        "time": 244,
        "reach": 431.276,
        "distance": 431.276,
        "leading": 199,
        "effort": 0,
        "arrival": 0
      },
      "velocity": {
        "gs": "2018-05-27T11:00:00Z",
        "ssVelocity": "20.03 km / h",
        "ssElapsed": "1.285278 h",
        "gsElapsed": "1.283889 h",
        "es": "2018-05-27T12:17:02Z",
        "ss": "2018-05-27T10:59:55Z",
        "ssDistance": "25.749 km",
        "gsVelocity": "20.10 km / h"
      },
      "total": 874,
      "landedDistance": "26.388 km",
      "place": "3",
      "reachDistance": "26.388 km"
    }
  ],
  [
    [
      "101",
      "Tomaž Toplak"
    ],
    {
      "breakdown": {
        "time": 200.9,
        "reach": 431.276,
        "distance": 431.276,
        "leading": 197.8,
        "effort": 0,
        "arrival": 0
      },
      "velocity": {
        "gs": "2018-05-27T11:00:00Z",
        "ssVelocity": "22.67 km / h",
        "ssElapsed": "1.135833 h",
        "gsElapsed": "1.398333 h",
        "es": "2018-05-27T12:23:54Z",
        "ss": "2018-05-27T11:15:45Z",
        "ssDistance": "25.749 km",
        "gsVelocity": "18.40 km / h"
      },
      "total": 830,
      "landedDistance": "26.388 km",
      "place": "4",
      "reachDistance": "26.388 km"
    }
  ],
  [
    [
      "74",
      "Nuno Filipe da Fonseca Bastos Gomes"
    ],
    {
      "breakdown": {
        "time": 181.4,
        "reach": 431.276,
        "distance": 431.276,
        "leading": 197.8,
        "effort": 0,
        "arrival": 0
      },
      "velocity": {
        "gs": "2018-05-27T11:00:00Z",
        "ssVelocity": "20.23 km / h",
        "ssElapsed": "1.273056 h",
        "gsElapsed": "1.455278 h",
        "es": "2018-05-27T12:27:19Z",
        "ss": "2018-05-27T11:10:56Z",
        "ssDistance": "25.749 km",
        "gsVelocity": "17.70 km / h"
      },
      "total": 811,
      "landedDistance": "26.388 km",
      "place": "5",
      "reachDistance": "26.388 km"
    }
  ],
  [
    [
      "73",
      "Mitja Jug"
    ],
    {
      "breakdown": {
        "time": 144.5,
        "reach": 431.276,
        "distance": 431.276,
        "leading": 197.9,
        "effort": 0,
        "arrival": 0
      },
      "velocity": {
        "gs": "2018-05-27T11:00:00Z",
        "ssVelocity": "16.95 km / h",
        "ssElapsed": "1.519167 h",
        "gsElapsed": "1.571667 h",
        "es": "2018-05-27T12:34:18Z",
        "ss": "2018-05-27T11:03:09Z",
        "ssDistance": "25.749 km",
        "gsVelocity": "16.40 km / h"
      },
      "total": 774,
      "landedDistance": "26.388 km",
      "place": "6",
      "reachDistance": "26.388 km"
    }
  ],
  [
    [
      "9",
      "Antoni Buljan"
    ],
    {
      "breakdown": {
        "time": 142,
        "reach": 431.276,
        "distance": 431.276,
        "leading": 197.5,
        "effort": 0,
        "arrival": 0
      },
      "velocity": {
        "gs": "2018-05-27T11:00:00Z",
        "ssVelocity": "19.63 km / h",
        "ssElapsed": "1.311667 h",
        "gsElapsed": "1.580000 h",
        "es": "2018-05-27T12:34:48Z",
        "ss": "2018-05-27T11:16:06Z",
        "ssDistance": "25.749 km",
        "gsVelocity": "16.30 km / h"
      },
      "total": 771,
      "landedDistance": "26.388 km",
      "place": "7",
      "reachDistance": "26.388 km"
    }
  ],
  [
    [
      "72",
      "Mitja Jančič"
    ],
    {
      "breakdown": {
        "time": 128.9,
        "reach": 431.276,
        "distance": 431.276,
        "leading": 197.7,
        "effort": 0,
        "arrival": 0
      },
      "velocity": {
        "gs": "2018-05-27T11:00:00Z",
        "ssVelocity": "16.09 km / h",
        "ssElapsed": "1.600000 h",
        "gsElapsed": "1.623889 h",
        "es": "2018-05-27T12:37:26Z",
        "ss": "2018-05-27T11:01:26Z",
        "ssDistance": "25.749 km",
        "gsVelocity": "15.90 km / h"
      },
      "total": 758,
      "landedDistance": "26.388 km",
      "place": "8",
      "reachDistance": "26.388 km"
    }
  ],
  [
    [
      "114",
      "Joan Brito"
    ],
    {
      "breakdown": {
        "time": 126.3,
        "reach": 431.276,
        "distance": 431.276,
        "leading": 198.2,
        "effort": 0,
        "arrival": 0
      },
      "velocity": {
        "gs": "2018-05-27T11:00:00Z",
        "ssVelocity": "15.90 km / h",
        "ssElapsed": "1.619444 h",
        "gsElapsed": "1.632500 h",
        "es": "2018-05-27T12:37:57Z",
        "ss": "2018-05-27T11:00:47Z",
        "ssDistance": "25.749 km",
        "gsVelocity": "15.80 km / h"
      },
      "total": 756,
      "landedDistance": "26.388 km",
      "place": "9",
      "reachDistance": "26.388 km"
    }
  ],
  [
    [
      "95",
      "Stojan Kranjc"
    ],
    {
      "breakdown": {
        "time": 89.4,
        "reach": 431.276,
        "distance": 431.276,
        "leading": 197.4,
        "effort": 0,
        "arrival": 0
      },
      "velocity": {
        "gs": "2018-05-27T11:00:00Z",
        "ssVelocity": "17.24 km / h",
        "ssElapsed": "1.493611 h",
        "gsElapsed": "1.763611 h",
        "es": "2018-05-27T12:45:49Z",
        "ss": "2018-05-27T11:16:12Z",
        "ssDistance": "25.749 km",
        "gsVelocity": "14.60 km / h"
      },
      "total": 718,
      "landedDistance": "26.388 km",
      "place": "10",
      "reachDistance": "26.388 km"
    }
  ],
  [
    [
      "63",
      "Marketa Tomaskova"
    ],
    {
      "breakdown": {
        "time": 12.4,
        "reach": 431.276,
        "distance": 431.276,
        "leading": 197.2,
        "effort": 0,
        "arrival": 0
      },
      "velocity": {
        "gs": "2018-05-27T11:00:00Z",
        "ssVelocity": "12.62 km / h",
        "ssElapsed": "2.041111 h",
        "gsElapsed": "2.064722 h",
        "es": "2018-05-27T13:03:53Z",
        "ss": "2018-05-27T11:01:25Z",
        "ssDistance": "25.749 km",
        "gsVelocity": "12.50 km / h"
      },
      "total": 641,
      "landedDistance": "26.388 km",
      "place": "11",
      "reachDistance": "26.388 km"
    }
  ],
  [
    [
      "54",
      "Krešo  Kovačič"
    ],
    {
      "breakdown": {
        "time": 0,
        "reach": 405.061,
        "distance": 405.061,
        "leading": 0,
        "effort": 0,
        "arrival": 0
      },
      "velocity": {
        "gs": "2018-05-27T11:00:00Z",
        "ssVelocity": null,
        "ssElapsed": null,
        "gsElapsed": null,
        "es": null,
        "ss": "2018-05-27T11:03:42Z",
        "ssDistance": null,
        "gsVelocity": null
      },
      "total": 405,
      "landedDistance": "24.671 km",
      "place": "12",
      "reachDistance": "24.784 km"
    }
  ],
  [
    [
      "37",
      "Igor Eržen"
    ],
    {
      "breakdown": {
        "time": 0,
        "reach": 377.294,
        "distance": 377.294,
        "leading": 0,
        "effort": 0,
        "arrival": 0
      },
      "velocity": {
        "gs": "2018-05-27T11:00:00Z",
        "ssVelocity": null,
        "ssElapsed": null,
        "gsElapsed": null,
        "es": null,
        "ss": "2018-05-27T11:02:32Z",
        "ssDistance": null,
        "gsVelocity": null
      },
      "total": 377,
      "landedDistance": "23.085 km",
      "place": "13",
      "reachDistance": "23.085 km"
    }
  ],
  [
    [
      "57",
      "Lara Leban"
    ],
    {
      "breakdown": {
        "time": 0,
        "reach": 375.087,
        "distance": 375.087,
        "leading": 0,
        "effort": 0,
        "arrival": 0
      },
      "velocity": {
        "gs": "2018-05-27T11:00:00Z",
        "ssVelocity": null,
        "ssElapsed": null,
        "gsElapsed": null,
        "es": null,
        "ss": "2018-05-27T11:04:19Z",
        "ssDistance": null,
        "gsVelocity": null
      },
      "total": 375,
      "landedDistance": "22.950 km",
      "place": "14",
      "reachDistance": "22.950 km"
    }
  ],
  [
    [
      "41",
      "Ivo Duarte"
    ],
    {
      "breakdown": {
        "time": 0,
        "reach": 364.088,
        "distance": 364.088,
        "leading": 0,
        "effort": 0,
        "arrival": 0
      },
      "velocity": {
        "gs": "2018-05-27T11:00:00Z",
        "ssVelocity": null,
        "ssElapsed": null,
        "gsElapsed": null,
        "es": null,
        "ss": "2018-05-27T11:03:12Z",
        "ssDistance": null,
        "gsVelocity": null
      },
      "total": 364,
      "landedDistance": "22.278 km",
      "place": "15",
      "reachDistance": "22.277 km"
    }
  ],
  [
    [
      "23",
      "David Šiljeg"
    ],
    {
      "breakdown": {
        "time": 0,
        "reach": 260.487,
        "distance": 260.487,
        "leading": 0,
        "effort": 0,
        "arrival": 0
      },
      "velocity": {
        "gs": "2018-05-27T11:00:00Z",
        "ssVelocity": null,
        "ssElapsed": null,
        "gsElapsed": null,
        "es": null,
        "ss": "2018-05-27T12:17:41Z",
        "ssDistance": null,
        "gsVelocity": null
      },
      "total": 260,
      "landedDistance": "14.230 km",
      "place": "16",
      "reachDistance": "15.938 km"
    }
  ],
  [
    [
      "80",
      "Ricardo Nicolau Soares Terra de Oliveira Figueiredo"
    ],
    {
      "breakdown": {
        "time": 0,
        "reach": 51.88,
        "distance": 51.88,
        "leading": 0,
        "effort": 0,
        "arrival": 0
      },
      "velocity": {
        "gs": "2018-05-27T11:00:00Z",
        "ssVelocity": null,
        "ssElapsed": null,
        "gsElapsed": null,
        "es": null,
        "ss": "2018-05-27T13:10:40Z",
        "ssDistance": null,
        "gsVelocity": null
      },
      "total": 52,
      "landedDistance": "3.172 km",
      "place": "17",
      "reachDistance": "3.174 km"
    }
  ],
  [
    [
      "46",
      "Jerko Odžak"
    ],
    {
      "breakdown": {
        "time": 0,
        "reach": 30.486,
        "distance": 30.486,
        "leading": 0,
        "effort": 0,
        "arrival": 0
      },
      "velocity": {
        "gs": "2018-05-27T11:00:00Z",
        "ssVelocity": null,
        "ssElapsed": null,
        "gsElapsed": null,
        "es": null,
        "ss": "2018-05-27T12:09:10Z",
        "ssDistance": null,
        "gsVelocity": null
      },
      "total": 30,
      "landedDistance": "-0.086 km",
      "place": "18",
      "reachDistance": "1.865 km"
    }
  ],
  [
    [
      "4",
      "Alojz Tovornik"
    ],
    {
      "breakdown": {
        "time": 0,
        "reach": 19.683,
        "distance": 19.683,
        "leading": 0,
        "effort": 0,
        "arrival": 0
      },
      "velocity": {
        "gs": "2018-05-27T11:00:00Z",
        "ssVelocity": null,
        "ssElapsed": null,
        "gsElapsed": null,
        "es": null,
        "ss": "2018-05-27T11:16:28Z",
        "ssDistance": null,
        "gsVelocity": null
      },
      "total": 20,
      "landedDistance": "0.744 km",
      "place": "19",
      "reachDistance": "1.204 km"
    }
  ],
  [
    [
      "40",
      "Ivica Huljek"
    ],
    {
      "breakdown": {
        "time": 0,
        "reach": 16.343,
        "distance": 16.343,
        "leading": 0,
        "effort": 0,
        "arrival": 0
      },
      "velocity": {
        "gs": "2018-05-27T11:00:00Z",
        "ssVelocity": null,
        "ssElapsed": null,
        "gsElapsed": null,
        "es": null,
        "ss": "2018-05-27T11:05:06Z",
        "ssDistance": null,
        "gsVelocity": null
      },
      "total": 16,
      "landedDistance": "-0.238 km",
      "place": "20=",
      "reachDistance": "0.125 km"
    }
  ],
  [
    [
      "91",
      "Slava Jelić"
    ],
    {
      "breakdown": {
        "time": 0,
        "reach": 16.343,
        "distance": 16.343,
        "leading": 0,
        "effort": 0,
        "arrival": 0
      },
      "velocity": null,
      "total": 16,
      "landedDistance": "0.000 km",
      "place": "20=",
      "reachDistance": "0.000 km"
    }
  ]
]
