[
  {
    "inter": {
      "time": "2018-05-27T10:19:12.574102215304Z",
      "lat": 43.8266142,
      "fixFrac": 63.57410221530478,
      "lng": 16.64497161,
      "alt": 752.57
    },
    "cross": {
      "inZone": [
        true,
        false
      ],
      "crossingPair": [
        {
          "time": "2018-05-27T10:19:12Z",
          "lat": 43.82663333,
          "fix": 63,
          "lng": 16.64493333,
          "alt": 752
        },
        {
          "time": "2018-05-27T10:19:13Z",
          "lat": 43.8266,
          "fix": 64,
          "lng": 16.645,
          "alt": 753
        }
      ]
    }
  },
  {
    "inter": {
      "time": "2018-05-27T11:00:48.924384422007Z",
      "lat": 43.83092045,
      "fixFrac": 2559.9243844220077,
      "lng": 16.6270563,
      "alt": 1120.08
    },
    "cross": {
      "inZone": [
        true,
        false
      ],
      "crossingPair": [
        {
          "time": "2018-05-27T11:00:48Z",
          "lat": 43.83096667,
          "fix": 2559,
          "lng": 16.62713333,
          "alt": 1121
        },
        {
          "time": "2018-05-27T11:00:49Z",
          "lat": 43.83091667,
          "fix": 2560,
          "lng": 16.62705,
          "alt": 1120
        }
      ]
    }
  },
  {
    "inter": {
      "time": "2018-05-27T11:02:15.757180497389Z",
      "lat": 43.82532023,
      "fixFrac": 2646.757180497389,
      "lng": 16.62004952,
      "alt": 1014.24
    },
    "cross": {
      "inZone": [
        false,
        true
      ],
      "crossingPair": [
        {
          "time": "2018-05-27T11:02:15Z",
          "lat": 43.82538333,
          "fix": 2646,
          "lng": 16.6201,
          "alt": 1015
        },
        {
          "time": "2018-05-27T11:02:16Z",
          "lat": 43.8253,
          "fix": 2647,
          "lng": 16.62003333,
          "alt": 1014
        }
      ]
    }
  },
  {
    "inter": {
      "time": "2018-05-27T11:08:17.550355088292Z",
      "lat": 43.8440125,
      "fixFrac": 3008.550355088293,
      "lng": 16.60587824,
      "alt": 1033
    },
    "cross": {
      "inZone": [
        false,
        true
      ],
      "crossingPair": [
        {
          "time": "2018-05-27T11:08:17Z",
          "lat": 43.84396667,
          "fix": 3008,
          "lng": 16.60593333,
          "alt": 1033
        },
        {
          "time": "2018-05-27T11:08:18Z",
          "lat": 43.84405,
          "fix": 3009,
          "lng": 16.60583333,
          "alt": 1033
        }
      ]
    }
  },
  {
    "inter": {
      "time": "2018-05-27T11:49:21.123441652917Z",
      "lat": 43.79962304,
      "fixFrac": 5472.123441652917,
      "lng": 16.67146667,
      "alt": 1101.88
    },
    "cross": {
      "inZone": [
        false,
        true
      ],
      "crossingPair": [
        {
          "time": "2018-05-27T11:49:21Z",
          "lat": 43.79963333,
          "fix": 5472,
          "lng": 16.67146667,
          "alt": 1102
        },
        {
          "time": "2018-05-27T11:49:22Z",
          "lat": 43.79955,
          "fix": 5473,
          "lng": 16.67146667,
          "alt": 1101
        }
      ]
    }
  },
  {
    "inter": {
      "time": "2018-05-27T12:03:29.264884069516Z",
      "lat": 43.84185444,
      "fixFrac": 6320.2648840695165,
      "lng": 16.60351027,
      "alt": 892.74
    },
    "cross": {
      "inZone": [
        false,
        true
      ],
      "crossingPair": [
        {
          "time": "2018-05-27T12:03:29Z",
          "lat": 43.84185,
          "fix": 6320,
          "lng": 16.60355,
          "alt": 893
        },
        {
          "time": "2018-05-27T12:03:30Z",
          "lat": 43.84186667,
          "fix": 6321,
          "lng": 16.6034,
          "alt": 892
        }
      ]
    }
  },
  {
    "inter": {
      "time": "2018-05-27T12:37:55.525162969042Z",
      "lat": 43.76205707,
      "fixFrac": 8386.525162969043,
      "lng": 16.62185,
      "alt": 535.42
    },
    "cross": {
      "inZone": [
        false,
        true
      ],
      "crossingPair": [
        {
          "time": "2018-05-27T12:37:55Z",
          "lat": 43.76208333,
          "fix": 8386,
          "lng": 16.62185,
          "alt": 537
        },
        {
          "time": "2018-05-27T12:37:56Z",
          "lat": 43.76203333,
          "fix": 8387,
          "lng": 16.62185,
          "alt": 534
        }
      ]
    }
  }
]
