{
  "zonesCrossNominees": [
    [
      {
        "inZone": [
          true,
          false
        ],
        "crossingPair": [
          {
            "time": "2018-05-27T10:57:24Z",
            "lat": 43.83205,
            "fix": 120,
            "lng": 16.63875,
            "alt": 912
          },
          {
            "time": "2018-05-27T10:57:29Z",
            "lat": 43.83213333,
            "fix": 121,
            "lng": 16.63825,
            "alt": 908
          }
        ]
      },
      {
        "inZone": [
          false,
          true
        ],
        "crossingPair": [
          {
            "time": "2018-05-27T11:29:19Z",
            "lat": 43.83246667,
            "fix": 527,
            "lng": 16.63883333,
            "alt": 890
          },
          {
            "time": "2018-05-27T11:29:24Z",
            "lat": 43.83221667,
            "fix": 528,
            "lng": 16.63928333,
            "alt": 886
          }
        ]
      },
      {
        "inZone": [
          true,
          false
        ],
        "crossingPair": [
          {
            "time": "2018-05-27T11:30:44Z",
            "lat": 43.82688333,
            "fix": 544,
            "lng": 16.64526667,
            "alt": 822
          },
          {
            "time": "2018-05-27T11:30:49Z",
            "lat": 43.82673333,
            "fix": 545,
            "lng": 16.64571667,
            "alt": 827
          }
        ]
      },
      {
        "inZone": [
          false,
          true
        ],
        "crossingPair": [
          {
            "time": "2018-05-27T11:30:49Z",
            "lat": 43.82673333,
            "fix": 545,
            "lng": 16.64571667,
            "alt": 827
          },
          {
            "time": "2018-05-27T11:30:54Z",
            "lat": 43.82715,
            "fix": 546,
            "lng": 16.6457,
            "alt": 830
          }
        ]
      },
      {
        "inZone": [
          true,
          false
        ],
        "crossingPair": [
          {
            "time": "2018-05-27T11:30:59Z",
            "lat": 43.8271,
            "fix": 547,
            "lng": 16.64528333,
            "alt": 831
          },
          {
            "time": "2018-05-27T11:31:04Z",
            "lat": 43.82683333,
            "fix": 548,
            "lng": 16.64546667,
            "alt": 840
          }
        ]
      },
      {
        "inZone": [
          false,
          true
        ],
        "crossingPair": [
          {
            "time": "2018-05-27T11:31:04Z",
            "lat": 43.82683333,
            "fix": 548,
            "lng": 16.64546667,
            "alt": 840
          },
          {
            "time": "2018-05-27T11:31:09Z",
            "lat": 43.82723333,
            "fix": 549,
            "lng": 16.6456,
            "alt": 846
          }
        ]
      },
      {
        "inZone": [
          true,
          false
        ],
        "crossingPair": [
          {
            "time": "2018-05-27T11:31:39Z",
            "lat": 43.8269,
            "fix": 555,
            "lng": 16.64543333,
            "alt": 865
          },
          {
            "time": "2018-05-27T11:31:44Z",
            "lat": 43.82676667,
            "fix": 556,
            "lng": 16.64591667,
            "alt": 870
          }
        ]
      },
      {
        "inZone": [
          false,
          true
        ],
        "crossingPair": [
          {
            "time": "2018-05-27T11:31:44Z",
            "lat": 43.82676667,
            "fix": 556,
            "lng": 16.64591667,
            "alt": 870
          },
          {
            "time": "2018-05-27T11:31:49Z",
            "lat": 43.82723333,
            "fix": 557,
            "lng": 16.6459,
            "alt": 872
          }
        ]
      },
      {
        "inZone": [
          true,
          false
        ],
        "crossingPair": [
          {
            "time": "2018-05-27T11:31:54Z",
            "lat": 43.82713333,
            "fix": 558,
            "lng": 16.64553333,
            "alt": 879
          },
          {
            "time": "2018-05-27T11:31:59Z",
            "lat": 43.82693333,
            "fix": 559,
            "lng": 16.64585,
            "alt": 882
          }
        ]
      },
      {
        "inZone": [
          false,
          true
        ],
        "crossingPair": [
          {
            "time": "2018-05-27T11:31:59Z",
            "lat": 43.82693333,
            "fix": 559,
            "lng": 16.64585,
            "alt": 882
          },
          {
            "time": "2018-05-27T11:32:04Z",
            "lat": 43.82735,
            "fix": 560,
            "lng": 16.64583333,
            "alt": 883
          }
        ]
      },
      {
        "inZone": [
          true,
          false
        ],
        "crossingPair": [
          {
            "time": "2018-05-27T11:32:09Z",
            "lat": 43.82713333,
            "fix": 561,
            "lng": 16.64555,
            "alt": 887
          },
          {
            "time": "2018-05-27T11:32:14Z",
            "lat": 43.82716667,
            "fix": 562,
            "lng": 16.64598333,
            "alt": 889
          }
        ]
      },
      {
        "inZone": [
          false,
          true
        ],
        "crossingPair": [
          {
            "time": "2018-05-27T11:32:14Z",
            "lat": 43.82716667,
            "fix": 562,
            "lng": 16.64598333,
            "alt": 889
          },
          {
            "time": "2018-05-27T11:32:19Z",
            "lat": 43.8276,
            "fix": 563,
            "lng": 16.64573333,
            "alt": 888
          }
        ]
      },
      {
        "inZone": [
          true,
          false
        ],
        "crossingPair": [
          {
            "time": "2018-05-27T11:32:29Z",
            "lat": 43.82705,
            "fix": 565,
            "lng": 16.64531667,
            "alt": 891
          },
          {
            "time": "2018-05-27T11:32:34Z",
            "lat": 43.82685,
            "fix": 566,
            "lng": 16.64578333,
            "alt": 889
          }
        ]
      },
      {
        "inZone": [
          false,
          true
        ],
        "crossingPair": [
          {
            "time": "2018-05-27T11:35:54Z",
            "lat": 43.82723333,
            "fix": 606,
            "lng": 16.64683333,
            "alt": 1086
          },
          {
            "time": "2018-05-27T11:35:59Z",
            "lat": 43.82766667,
            "fix": 607,
            "lng": 16.64646667,
            "alt": 1090
          }
        ]
      },
      {
        "inZone": [
          true,
          false
        ],
        "crossingPair": [
          {
            "time": "2018-05-27T11:36:04Z",
            "lat": 43.82741667,
            "fix": 608,
            "lng": 16.6462,
            "alt": 1102
          },
          {
            "time": "2018-05-27T11:36:09Z",
            "lat": 43.82723333,
            "fix": 609,
            "lng": 16.6466,
            "alt": 1110
          }
        ]
      },
      {
        "inZone": [
          false,
          true
        ],
        "crossingPair": [
          {
            "time": "2018-05-27T11:36:14Z",
            "lat": 43.82768333,
            "fix": 610,
            "lng": 16.64668333,
            "alt": 1114
          },
          {
            "time": "2018-05-27T11:36:19Z",
            "lat": 43.8277,
            "fix": 611,
            "lng": 16.64616667,
            "alt": 1123
          }
        ]
      },
      {
        "inZone": [
          true,
          false
        ],
        "crossingPair": [
          {
            "time": "2018-05-27T11:36:19Z",
            "lat": 43.8277,
            "fix": 611,
            "lng": 16.64616667,
            "alt": 1123
          },
          {
            "time": "2018-05-27T11:36:24Z",
            "lat": 43.82735,
            "fix": 612,
            "lng": 16.64635,
            "alt": 1134
          }
        ]
      },
      {
        "inZone": [
          false,
          true
        ],
        "crossingPair": [
          {
            "time": "2018-05-27T11:36:29Z",
            "lat": 43.8276,
            "fix": 613,
            "lng": 16.64673333,
            "alt": 1140
          },
          {
            "time": "2018-05-27T11:36:34Z",
            "lat": 43.82783333,
            "fix": 614,
            "lng": 16.6462,
            "alt": 1146
          }
        ]
      },
      {
        "inZone": [
          true,
          false
        ],
        "crossingPair": [
          {
            "time": "2018-05-27T11:36:39Z",
            "lat": 43.82748333,
            "fix": 615,
            "lng": 16.64615,
            "alt": 1155
          },
          {
            "time": "2018-05-27T11:36:44Z",
            "lat": 43.82748333,
            "fix": 616,
            "lng": 16.64655,
            "alt": 1160
          }
        ]
      },
      {
        "inZone": [
          false,
          true
        ],
        "crossingPair": [
          {
            "time": "2018-05-27T11:36:44Z",
            "lat": 43.82748333,
            "fix": 616,
            "lng": 16.64655,
            "alt": 1160
          },
          {
            "time": "2018-05-27T11:36:49Z",
            "lat": 43.82795,
            "fix": 617,
            "lng": 16.64633333,
            "alt": 1163
          }
        ]
      },
      {
        "inZone": [
          true,
          false
        ],
        "crossingPair": [
          {
            "time": "2018-05-27T11:36:59Z",
            "lat": 43.82745,
            "fix": 619,
            "lng": 16.64605,
            "alt": 1175
          },
          {
            "time": "2018-05-27T11:37:04Z",
            "lat": 43.82721667,
            "fix": 620,
            "lng": 16.64643333,
            "alt": 1174
          }
        ]
      },
      {
        "inZone": [
          false,
          true
        ],
        "crossingPair": [
          {
            "time": "2018-05-27T11:53:34Z",
            "lat": 43.82691667,
            "fix": 826,
            "lng": 16.64581667,
            "alt": 1017
          },
          {
            "time": "2018-05-27T11:53:39Z",
            "lat": 43.82715,
            "fix": 827,
            "lng": 16.64516667,
            "alt": 1011
          }
        ]
      },
      {
        "inZone": [
          true,
          false
        ],
        "crossingPair": [
          {
            "time": "2018-05-27T11:54:44Z",
            "lat": 43.83038333,
            "fix": 840,
            "lng": 16.6379,
            "alt": 948
          },
          {
            "time": "2018-05-27T11:54:49Z",
            "lat": 43.83065,
            "fix": 841,
            "lng": 16.63721667,
            "alt": 940
          }
        ]
      }
    ],
    [
      {
        "inZone": [
          true,
          false
        ],
        "crossingPair": [
          {
            "time": "2018-05-27T11:03:10Z",
            "lat": 43.83135,
            "fix": 191,
            "lng": 16.6268,
            "alt": 985
          },
          {
            "time": "2018-05-27T11:03:11Z",
            "lat": 43.8313,
            "fix": 192,
            "lng": 16.62668333,
            "alt": 984
          }
        ]
      },
      {
        "inZone": [
          false,
          true
        ],
        "crossingPair": [
          {
            "time": "2018-05-27T11:26:24Z",
            "lat": 43.83321667,
            "fix": 492,
            "lng": 16.62533333,
            "alt": 917
          },
          {
            "time": "2018-05-27T11:26:29Z",
            "lat": 43.8332,
            "fix": 493,
            "lng": 16.62591667,
            "alt": 914
          }
        ]
      },
      {
        "inZone": [
          true,
          false
        ],
        "crossingPair": [
          {
            "time": "2018-05-27T11:38:59Z",
            "lat": 43.81761667,
            "fix": 643,
            "lng": 16.65405,
            "alt": 1021
          },
          {
            "time": "2018-05-27T11:39:04Z",
            "lat": 43.8172,
            "fix": 644,
            "lng": 16.65435,
            "alt": 1020
          }
        ]
      },
      {
        "inZone": [
          false,
          true
        ],
        "crossingPair": [
          {
            "time": "2018-05-27T11:49:09Z",
            "lat": 43.81655,
            "fix": 773,
            "lng": 16.65756667,
            "alt": 903
          },
          {
            "time": "2018-05-27T11:49:14Z",
            "lat": 43.81713333,
            "fix": 774,
            "lng": 16.65711667,
            "alt": 903
          }
        ]
      },
      {
        "inZone": [
          true,
          false
        ],
        "crossingPair": [
          {
            "time": "2018-05-27T11:56:14Z",
            "lat": 43.83301667,
            "fix": 858,
            "lng": 16.6259,
            "alt": 869
          },
          {
            "time": "2018-05-27T11:56:19Z",
            "lat": 43.83301667,
            "fix": 859,
            "lng": 16.62511667,
            "alt": 863
          }
        ]
      }
    ],
    [
      {
        "inZone": [
          false,
          true
        ],
        "crossingPair": [
          {
            "time": "2018-05-27T11:05:39Z",
            "lat": 43.82638333,
            "fix": 225,
            "lng": 16.61883333,
            "alt": 927
          },
          {
            "time": "2018-05-27T11:05:42Z",
            "lat": 43.82611667,
            "fix": 226,
            "lng": 16.61861667,
            "alt": 921
          }
        ]
      },
      {
        "inZone": [
          true,
          false
        ],
        "crossingPair": [
          {
            "time": "2018-05-27T11:05:54Z",
            "lat": 43.82631667,
            "fix": 234,
            "lng": 16.61755,
            "alt": 902
          },
          {
            "time": "2018-05-27T11:05:59Z",
            "lat": 43.82666667,
            "fix": 235,
            "lng": 16.61703333,
            "alt": 889
          }
        ]
      },
      {
        "inZone": [
          false,
          true
        ],
        "crossingPair": [
          {
            "time": "2018-05-27T12:17:09Z",
            "lat": 43.8242,
            "fix": 1116,
            "lng": 16.62128333,
            "alt": 965
          },
          {
            "time": "2018-05-27T12:17:14Z",
            "lat": 43.8239,
            "fix": 1117,
            "lng": 16.62078333,
            "alt": 966
          }
        ]
      },
      {
        "inZone": [
          true,
          false
        ],
        "crossingPair": [
          {
            "time": "2018-05-27T12:23:04Z",
            "lat": 43.82066667,
            "fix": 1187,
            "lng": 16.62016667,
            "alt": 1325
          },
          {
            "time": "2018-05-27T12:23:09Z",
            "lat": 43.8202,
            "fix": 1188,
            "lng": 16.62031667,
            "alt": 1317
          }
        ]
      }
    ],
    [
      {
        "inZone": [
          false,
          true
        ],
        "crossingPair": [
          {
            "time": "2018-05-27T11:15:14Z",
            "lat": 43.84125,
            "fix": 346,
            "lng": 16.60293333,
            "alt": 897
          },
          {
            "time": "2018-05-27T11:15:19Z",
            "lat": 43.84148333,
            "fix": 347,
            "lng": 16.60235,
            "alt": 901
          }
        ]
      },
      {
        "inZone": [
          true,
          false
        ],
        "crossingPair": [
          {
            "time": "2018-05-27T11:15:49Z",
            "lat": 43.84133333,
            "fix": 365,
            "lng": 16.60231667,
            "alt": 879
          },
          {
            "time": "2018-05-27T11:15:54Z",
            "lat": 43.8411,
            "fix": 366,
            "lng": 16.60268333,
            "alt": 874
          }
        ]
      },
      {
        "inZone": [
          false,
          true
        ],
        "crossingPair": [
          {
            "time": "2018-05-27T11:59:59Z",
            "lat": 43.83871667,
            "fix": 903,
            "lng": 16.60065,
            "alt": 789
          },
          {
            "time": "2018-05-27T12:00:04Z",
            "lat": 43.8389,
            "fix": 904,
            "lng": 16.60008333,
            "alt": 792
          }
        ]
      },
      {
        "inZone": [
          true,
          false
        ],
        "crossingPair": [
          {
            "time": "2018-05-27T12:01:59Z",
            "lat": 43.83956667,
            "fix": 934,
            "lng": 16.60046667,
            "alt": 819
          },
          {
            "time": "2018-05-27T12:02:04Z",
            "lat": 43.83928333,
            "fix": 935,
            "lng": 16.60061667,
            "alt": 823
          }
        ]
      },
      {
        "inZone": [
          false,
          true
        ],
        "crossingPair": [
          {
            "time": "2018-05-27T12:02:19Z",
            "lat": 43.83908333,
            "fix": 938,
            "lng": 16.60076667,
            "alt": 834
          },
          {
            "time": "2018-05-27T12:02:24Z",
            "lat": 43.83955,
            "fix": 939,
            "lng": 16.60033333,
            "alt": 840
          }
        ]
      },
      {
        "inZone": [
          true,
          false
        ],
        "crossingPair": [
          {
            "time": "2018-05-27T12:04:09Z",
            "lat": 43.84016667,
            "fix": 960,
            "lng": 16.60155,
            "alt": 901
          },
          {
            "time": "2018-05-27T12:04:14Z",
            "lat": 43.83995,
            "fix": 961,
            "lng": 16.60183333,
            "alt": 892
          }
        ]
      }
    ],
    [
      {
        "inZone": [
          false,
          true
        ],
        "crossingPair": [
          {
            "time": "2018-05-27T11:46:25Z",
            "lat": 43.7997,
            "fix": 733,
            "lng": 16.6718,
            "alt": 1134
          },
          {
            "time": "2018-05-27T11:46:26Z",
            "lat": 43.79963333,
            "fix": 734,
            "lng": 16.6718,
            "alt": 1134
          }
        ]
      },
      {
        "inZone": [
          true,
          false
        ],
        "crossingPair": [
          {
            "time": "2018-05-27T11:46:34Z",
            "lat": 43.79958333,
            "fix": 742,
            "lng": 16.67133333,
            "alt": 1138
          },
          {
            "time": "2018-05-27T11:46:39Z",
            "lat": 43.79995,
            "fix": 743,
            "lng": 16.67101667,
            "alt": 1136
          }
        ]
      }
    ],
    [
      {
        "inZone": [
          false,
          true
        ],
        "crossingPair": [
          {
            "time": "2018-05-27T11:15:14Z",
            "lat": 43.84125,
            "fix": 346,
            "lng": 16.60293333,
            "alt": 897
          },
          {
            "time": "2018-05-27T11:15:19Z",
            "lat": 43.84148333,
            "fix": 347,
            "lng": 16.60235,
            "alt": 901
          }
        ]
      },
      {
        "inZone": [
          true,
          false
        ],
        "crossingPair": [
          {
            "time": "2018-05-27T11:15:49Z",
            "lat": 43.84133333,
            "fix": 365,
            "lng": 16.60231667,
            "alt": 879
          },
          {
            "time": "2018-05-27T11:15:54Z",
            "lat": 43.8411,
            "fix": 366,
            "lng": 16.60268333,
            "alt": 874
          }
        ]
      },
      {
        "inZone": [
          false,
          true
        ],
        "crossingPair": [
          {
            "time": "2018-05-27T11:59:59Z",
            "lat": 43.83871667,
            "fix": 903,
            "lng": 16.60065,
            "alt": 789
          },
          {
            "time": "2018-05-27T12:00:04Z",
            "lat": 43.8389,
            "fix": 904,
            "lng": 16.60008333,
            "alt": 792
          }
        ]
      },
      {
        "inZone": [
          true,
          false
        ],
        "crossingPair": [
          {
            "time": "2018-05-27T12:01:59Z",
            "lat": 43.83956667,
            "fix": 934,
            "lng": 16.60046667,
            "alt": 819
          },
          {
            "time": "2018-05-27T12:02:04Z",
            "lat": 43.83928333,
            "fix": 935,
            "lng": 16.60061667,
            "alt": 823
          }
        ]
      },
      {
        "inZone": [
          false,
          true
        ],
        "crossingPair": [
          {
            "time": "2018-05-27T12:02:19Z",
            "lat": 43.83908333,
            "fix": 938,
            "lng": 16.60076667,
            "alt": 834
          },
          {
            "time": "2018-05-27T12:02:24Z",
            "lat": 43.83955,
            "fix": 939,
            "lng": 16.60033333,
            "alt": 840
          }
        ]
      },
      {
        "inZone": [
          true,
          false
        ],
        "crossingPair": [
          {
            "time": "2018-05-27T12:04:09Z",
            "lat": 43.84016667,
            "fix": 960,
            "lng": 16.60155,
            "alt": 901
          },
          {
            "time": "2018-05-27T12:04:14Z",
            "lat": 43.83995,
            "fix": 961,
            "lng": 16.60183333,
            "alt": 892
          }
        ]
      }
    ],
    [
      {
        "inZone": [
          false,
          true
        ],
        "crossingPair": [
          {
            "time": "2018-05-27T12:34:16Z",
            "lat": 43.76181667,
            "fix": 1322,
            "lng": 16.6232,
            "alt": 473
          },
          {
            "time": "2018-05-27T12:34:17Z",
            "lat": 43.76173333,
            "fix": 1323,
            "lng": 16.62318333,
            "alt": 472
          }
        ]
      },
      {
        "inZone": [
          true,
          false
        ],
        "crossingPair": [
          {
            "time": "2018-05-27T12:34:59Z",
            "lat": 43.76168333,
            "fix": 1337,
            "lng": 16.6232,
            "alt": 412
          },
          {
            "time": "2018-05-27T12:35:00Z",
            "lat": 43.7618,
            "fix": 1338,
            "lng": 16.62325,
            "alt": 411
          }
        ]
      },
      {
        "inZone": [
          false,
          true
        ],
        "crossingPair": [
          {
            "time": "2018-05-27T12:35:14Z",
            "lat": 43.7618,
            "fix": 1345,
            "lng": 16.62348333,
            "alt": 387
          },
          {
            "time": "2018-05-27T12:35:19Z",
            "lat": 43.76165,
            "fix": 1346,
            "lng": 16.62338333,
            "alt": 387
          }
        ]
      }
    ]
  ],
  "zonesCrossExcluded": [],
  "startSelected": [
    "2018-05-27T11:00:00Z",
    {
      "inZone": [
        true,
        false
      ],
      "crossingPair": [
        {
          "time": "2018-05-27T11:03:10Z",
          "lat": 43.83135,
          "fix": 191,
          "lng": 16.6268,
          "alt": 985
        },
        {
          "time": "2018-05-27T11:03:11Z",
          "lat": 43.8313,
          "fix": 192,
          "lng": 16.62668333,
          "alt": 984
        }
      ]
    }
  ],
  "zonesCrossSelected": [
    {
      "inZone": [
        true,
        false
      ],
      "crossingPair": [
        {
          "time": "2018-05-27T10:57:24Z",
          "lat": 43.83205,
          "fix": 120,
          "lng": 16.63875,
          "alt": 912
        },
        {
          "time": "2018-05-27T10:57:29Z",
          "lat": 43.83213333,
          "fix": 121,
          "lng": 16.63825,
          "alt": 908
        }
      ]
    },
    {
      "inZone": [
        true,
        false
      ],
      "crossingPair": [
        {
          "time": "2018-05-27T11:03:10Z",
          "lat": 43.83135,
          "fix": 191,
          "lng": 16.6268,
          "alt": 985
        },
        {
          "time": "2018-05-27T11:03:11Z",
          "lat": 43.8313,
          "fix": 192,
          "lng": 16.62668333,
          "alt": 984
        }
      ]
    },
    {
      "inZone": [
        false,
        true
      ],
      "crossingPair": [
        {
          "time": "2018-05-27T11:05:39Z",
          "lat": 43.82638333,
          "fix": 225,
          "lng": 16.61883333,
          "alt": 927
        },
        {
          "time": "2018-05-27T11:05:42Z",
          "lat": 43.82611667,
          "fix": 226,
          "lng": 16.61861667,
          "alt": 921
        }
      ]
    },
    {
      "inZone": [
        false,
        true
      ],
      "crossingPair": [
        {
          "time": "2018-05-27T11:15:14Z",
          "lat": 43.84125,
          "fix": 346,
          "lng": 16.60293333,
          "alt": 897
        },
        {
          "time": "2018-05-27T11:15:19Z",
          "lat": 43.84148333,
          "fix": 347,
          "lng": 16.60235,
          "alt": 901
        }
      ]
    },
    {
      "inZone": [
        false,
        true
      ],
      "crossingPair": [
        {
          "time": "2018-05-27T11:46:25Z",
          "lat": 43.7997,
          "fix": 733,
          "lng": 16.6718,
          "alt": 1134
        },
        {
          "time": "2018-05-27T11:46:26Z",
          "lat": 43.79963333,
          "fix": 734,
          "lng": 16.6718,
          "alt": 1134
        }
      ]
    },
    {
      "inZone": [
        false,
        true
      ],
      "crossingPair": [
        {
          "time": "2018-05-27T11:59:59Z",
          "lat": 43.83871667,
          "fix": 903,
          "lng": 16.60065,
          "alt": 789
        },
        {
          "time": "2018-05-27T12:00:04Z",
          "lat": 43.8389,
          "fix": 904,
          "lng": 16.60008333,
          "alt": 792
        }
      ]
    },
    {
      "inZone": [
        false,
        true
      ],
      "crossingPair": [
        {
          "time": "2018-05-27T12:34:16Z",
          "lat": 43.76181667,
          "fix": 1322,
          "lng": 16.6232,
          "alt": 473
        },
        {
          "time": "2018-05-27T12:34:17Z",
          "lat": 43.76173333,
          "fix": 1323,
          "lng": 16.62318333,
          "alt": 472
        }
      ]
    }
  ],
  "startNominees": [
    [
      "2018-05-27T11:00:00Z",
      [
        {
          "inZone": [
            true,
            false
          ],
          "crossingPair": [
            {
              "time": "2018-05-27T11:03:10Z",
              "lat": 43.83135,
              "fix": 191,
              "lng": 16.6268,
              "alt": 985
            },
            {
              "time": "2018-05-27T11:03:11Z",
              "lat": 43.8313,
              "fix": 192,
              "lng": 16.62668333,
              "alt": 984
            }
          ]
        },
        {
          "inZone": [
            true,
            false
          ],
          "crossingPair": [
            {
              "time": "2018-05-27T11:38:59Z",
              "lat": 43.81761667,
              "fix": 643,
              "lng": 16.65405,
              "alt": 1021
            },
            {
              "time": "2018-05-27T11:39:04Z",
              "lat": 43.8172,
              "fix": 644,
              "lng": 16.65435,
              "alt": 1020
            }
          ]
        },
        {
          "inZone": [
            true,
            false
          ],
          "crossingPair": [
            {
              "time": "2018-05-27T11:56:14Z",
              "lat": 43.83301667,
              "fix": 858,
              "lng": 16.6259,
              "alt": 869
            },
            {
              "time": "2018-05-27T11:56:19Z",
              "lat": 43.83301667,
              "fix": 859,
              "lng": 16.62511667,
              "alt": 863
            }
          ]
        }
      ]
    ]
  ]
}
