{
  "taskRoute": {
    "waypoints": [
      {
        "lat": 43.82902992,
        "lng": 16.63755205
      },
      {
        "lat": 43.82796167,
        "lng": 16.63000567
      },
      {
        "lat": 43.82638317,
        "lng": 16.61769544
      },
      {
        "lat": 43.83894549,
        "lng": 16.5987078
      },
      {
        "lat": 43.79799144,
        "lng": 16.66804445
      },
      {
        "lat": 43.8277194,
        "lng": 16.5834812
      },
      {
        "lat": 43.76182738,
        "lng": 16.61756817
      }
    ],
    "flipSum": [
      "26.273235 km",
      "25.654732 km",
      "24.649102 km",
      "22.580151 km",
      "15.381434 km",
      "7.818272 km"
    ],
    "distance": "26.273235 km",
    "legsSum": [
      "0.618503 km",
      "1.624133 km",
      "3.693085 km",
      "10.891801 km",
      "18.454963 km",
      "26.273235 km"
    ],
    "legs": [
      "0.618503 km",
      "1.005630 km",
      "2.068951 km",
      "7.198717 km",
      "7.563162 km",
      "7.818272 km"
    ]
  },
  "startRoute": {
    "waypoints": [
      {
        "lat": 43.82853595,
        "lng": 16.63773864
      },
      {
        "lat": 43.82682764,
        "lng": 16.63124163
      },
      {
        "lat": 43.82412386,
        "lng": 16.62098102
      }
    ],
    "flipSum": [
      "1.434352 km",
      "0.878345 km"
    ],
    "distance": "1.434352 km",
    "legsSum": [
      "0.556007 km",
      "1.434352 km"
    ],
    "legs": [
      "0.556007 km",
      "0.878345 km"
    ]
  },
  "taskRouteSpeedSubset": {
    "waypoints": [
      {
        "lat": 43.82796167,
        "lng": 16.63000567
      },
      {
        "lat": 43.82638317,
        "lng": 16.61769544
      },
      {
        "lat": 43.83894549,
        "lng": 16.5987078
      },
      {
        "lat": 43.79799144,
        "lng": 16.66804445
      },
      {
        "lat": 43.8277194,
        "lng": 16.5834812
      },
      {
        "lat": 43.76182738,
        "lng": 16.61756817
      }
    ],
    "flipSum": [
      "25.654732 km",
      "24.649102 km",
      "22.580151 km",
      "15.381434 km",
      "7.818272 km"
    ],
    "distance": "25.654732 km",
    "legsSum": [
      "1.005630 km",
      "3.074582 km",
      "10.273298 km",
      "17.836460 km",
      "25.654732 km"
    ],
    "legs": [
      "1.005630 km",
      "2.068951 km",
      "7.198717 km",
      "7.563162 km",
      "7.818272 km"
    ]
  },
  "speedRoute": {
    "waypoints": [
      {
        "lat": 43.8307799,
        "lng": 16.62746127
      },
      {
        "lat": 43.82650166,
        "lng": 16.61691183
      },
      {
        "lat": 43.83894549,
        "lng": 16.5987078
      },
      {
        "lat": 43.79799144,
        "lng": 16.66804445
      },
      {
        "lat": 43.8277194,
        "lng": 16.5834812
      },
      {
        "lat": 43.76182738,
        "lng": 16.61756817
      }
    ],
    "flipSum": [
      "25.566597 km",
      "24.593964 km",
      "22.580151 km",
      "15.381434 km",
      "7.818272 km"
    ],
    "distance": "25.566597 km",
    "legsSum": [
      "0.972633 km",
      "2.986446 km",
      "10.185163 km",
      "17.748325 km",
      "25.566597 km"
    ],
    "legs": [
      "0.972633 km",
      "2.013813 km",
      "7.198717 km",
      "7.563162 km",
      "7.818272 km"
    ]
  },
  "stopRoute": {
    "waypoints": [
      {
        "lat": 43.82902992,
        "lng": 16.63755205
      },
      {
        "lat": 43.82796167,
        "lng": 16.63000567
      },
      {
        "lat": 43.82638317,
        "lng": 16.61769544
      },
      {
        "lat": 43.83894549,
        "lng": 16.5987078
      },
      {
        "lat": 43.79799144,
        "lng": 16.66804445
      },
      {
        "lat": 43.8277194,
        "lng": 16.5834812
      },
      {
        "lat": 43.76182738,
        "lng": 16.61756817
      }
    ],
    "flipSum": [
      "26.273235 km",
      "25.654732 km",
      "24.649102 km",
      "22.580151 km",
      "15.381434 km",
      "7.818272 km"
    ],
    "distance": "26.273235 km",
    "legsSum": [
      "0.618503 km",
      "1.624133 km",
      "3.693085 km",
      "10.891801 km",
      "18.454963 km",
      "26.273235 km"
    ],
    "legs": [
      "0.618503 km",
      "1.005630 km",
      "2.068951 km",
      "7.198717 km",
      "7.563162 km",
      "7.818272 km"
    ]
  }
}
